django_log_formatter_ecs/__init__.py
django_log_formatter_ecs-0.0.7.dist-info/LICENSE
django_log_formatter_ecs-0.0.7.dist-info/METADATA
django_log_formatter_ecs-0.0.7.dist-info/WHEEL
django_log_formatter_ecs-0.0.7.dist-info/RECORD
