Metadata-Version: 2.3
Name: django-log-formatter-ecs
Version: 0.0.7
Summary: Formats Django logs in ECS format.
License: MIT
Author: Department for Business and Trade Platform Team
Author-email: sre-team@digital.trade.gov.uk
Requires-Python: >=3.8,<4
Classifier: License :: OSI Approved :: MIT License
Classifier: Programming Language :: Python :: 3
Classifier: Programming Language :: Python :: 3.8
Classifier: Programming Language :: Python :: 3.9
Classifier: Programming Language :: Python :: 3.10
Classifier: Programming Language :: Python :: 3.11
Classifier: Programming Language :: Python :: 3.12
Classifier: Programming Language :: Python :: 3.13
Requires-Dist: django (>=4.2.15,<5.0.0)
Requires-Dist: django-ipware (>=7.0.0,<8.0.0)
Requires-Dist: kubi-ecs-logger (>=0.1.2,<0.2.0)
